parsec/__init__.py
parsec/cli.py
parsec/config.py
parsec/decorators.py
parsec/galaxy.py
parsec/io.py
parsec/commands/__init__.py
parsec/commands/cmd_config.py
parsec/commands/cmd_dataset_collections.py
parsec/commands/cmd_datasets.py
parsec/commands/cmd_datatypes.py
parsec/commands/cmd_folders.py
parsec/commands/cmd_forms.py
parsec/commands/cmd_ftpfiles.py
parsec/commands/cmd_genomes.py
parsec/commands/cmd_groups.py
parsec/commands/cmd_histories.py
parsec/commands/cmd_init.py
parsec/commands/cmd_invocations.py
parsec/commands/cmd_jobs.py
parsec/commands/cmd_libraries.py
parsec/commands/cmd_quotas.py
parsec/commands/cmd_roles.py
parsec/commands/cmd_toolShed.py
parsec/commands/cmd_tool_data.py
parsec/commands/cmd_tool_dependencies.py
parsec/commands/cmd_tools.py
parsec/commands/cmd_toolshed.py
parsec/commands/cmd_toolshed_categories.py
parsec/commands/cmd_toolshed_repositories.py
parsec/commands/cmd_toolshed_tools.py
parsec/commands/cmd_users.py
parsec/commands/cmd_utils.py
parsec/commands/cmd_visual.py
parsec/commands/cmd_workflows.py
parsec/commands/core.py
parsec/commands/config/__init__.py
parsec/commands/config/get_config.py
parsec/commands/config/get_version.py
parsec/commands/dataset_collections/__init__.py
parsec/commands/dataset_collections/download_dataset_collection.py
parsec/commands/dataset_collections/show_dataset_collection.py
parsec/commands/dataset_collections/wait_for_dataset_collection.py
parsec/commands/datasets/__init__.py
parsec/commands/datasets/download_dataset.py
parsec/commands/datasets/get_datasets.py
parsec/commands/datasets/publish_dataset.py
parsec/commands/datasets/show_dataset.py
parsec/commands/datasets/update_permissions.py
parsec/commands/datasets/wait_for_dataset.py
parsec/commands/datatypes/__init__.py
parsec/commands/datatypes/get_datatypes.py
parsec/commands/datatypes/get_sniffers.py
parsec/commands/folders/__init__.py
parsec/commands/folders/create_folder.py
parsec/commands/folders/delete_folder.py
galaxy_parsec-1.16.0.dist-info/LICENSE
galaxy_parsec-1.16.0.dist-info/METADATA
galaxy_parsec-1.16.0.dist-info/WHEEL
galaxy_parsec-1.16.0.dist-info/entry_points.txt
galaxy_parsec-1.16.0.dist-info/top_level.txt
galaxy_parsec-1.16.0.dist-info/RECORD
