Metadata-Version: 2.1
Name: galaxy-parsec
Version: 1.16.0
Summary: Command-line utilities to assist in interacting with Galaxy servers (http://galaxyproject.org/).
Home-page: https://github.com/galaxy-iuc/parsec
Author: Galaxy Project and Community
Author-email: parsec@hx42.org
License: AFL
Keywords: parsec
Platform: UNKNOWN
Classifier: Development Status :: 4 - Beta
Classifier: Intended Audience :: Developers
Classifier: Environment :: Console
Classifier: License :: OSI Approved :: MIT License
Classifier: Operating System :: POSIX
Classifier: Natural Language :: English
Classifier: Programming Language :: Python :: 3.6
Requires-Dist: Click (>=6.7)
Requires-Dist: bioblend (==0.16.0)
Requires-Dist: wrapt
Requires-Dist: pyyaml
Requires-Dist: justbackoff
Requires-Dist: xunit-wrapper (>=0.12)
Requires-Dist: future
